llm7_image/__init__.py
llm7_image-2025.6.141317.dist-info/licenses/LICENSE
llm7_image-2025.6.141317.dist-info/METADATA
llm7_image-2025.6.141317.dist-info/WHEEL
llm7_image-2025.6.141317.dist-info/top_level.txt
llm7_image-2025.6.141317.dist-info/RECORD
